textcounts/__init__.py
textcounts/core.py
textcounts/tests.py
textcounts-0.0.2.dist-info/DESCRIPTION.rst
textcounts-0.0.2.dist-info/METADATA
textcounts-0.0.2.dist-info/RECORD
textcounts-0.0.2.dist-info/WHEEL
textcounts-0.0.2.dist-info/metadata.json
textcounts-0.0.2.dist-info/top_level.txt
