Metadata-Version: 2.0
Name: textcounts
Version: 0.0.2
Summary: Frequency and proportion counts for series of search strings
Home-page: http://github.com/staeiou/textcounts
Author: Stuart Geiger
Author-email: stuart@stuartgeiger.com
License: MIT
Platform: UNKNOWN
Requires-Dist: pandas
